detkit/__init__.py
detkit/__version__.py
detkit/datasets/covariance_matrix.py
detkit/datasets/design_matrix.py
detkit/datasets/electrocardiogram.py
detkit/datasets/__init__.py
detkit/_benchmark/benchmark.cpp
detkit/_benchmark/benchmark.h
detkit/_benchmark/benchmark.pxd
detkit/_benchmark/get_instructions_per_flop.cp313-win_amd64.pyd
detkit/_benchmark/get_instructions_per_flop.pyx
detkit/_benchmark/__init__.pxd
detkit/_benchmark/__init__.py
detkit/_cy_linear_algebra/cho_factor.cp313-win_amd64.pyd
detkit/_cy_linear_algebra/cho_factor.pyx
detkit/_cy_linear_algebra/cho_solve.cp313-win_amd64.pyd
detkit/_cy_linear_algebra/cho_solve.pyx
detkit/_cy_linear_algebra/fill_triangle.cp313-win_amd64.pyd
detkit/_cy_linear_algebra/fill_triangle.pyx
detkit/_cy_linear_algebra/ldl_factor.cp313-win_amd64.pyd
detkit/_cy_linear_algebra/ldl_factor.pyx
detkit/_cy_linear_algebra/ldl_solve.cp313-win_amd64.pyd
detkit/_cy_linear_algebra/ldl_solve.pyx
detkit/_cy_linear_algebra/lu_factor.cp313-win_amd64.pyd
detkit/_cy_linear_algebra/lu_factor.pyx
detkit/_cy_linear_algebra/lu_solve.cp313-win_amd64.pyd
detkit/_cy_linear_algebra/lu_solve.pyx
detkit/_cy_linear_algebra/matmul.cp313-win_amd64.pyd
detkit/_cy_linear_algebra/matmul.pyx
detkit/_cy_linear_algebra/solve_diag.cp313-win_amd64.pyd
detkit/_cy_linear_algebra/solve_diag.pyx
detkit/_cy_linear_algebra/solve_triangular.cp313-win_amd64.pyd
detkit/_cy_linear_algebra/solve_triangular.pyx
detkit/_cy_linear_algebra/__init__.py
detkit/_c_basic_algebra/c_matrix_operations.cpp
detkit/_c_basic_algebra/c_matrix_operations.h
detkit/_c_basic_algebra/c_vector_operations.cpp
detkit/_c_basic_algebra/c_vector_operations.h
detkit/_c_basic_algebra/c_vector_operations.pxd
detkit/_c_basic_algebra/__init__.pxd
detkit/_c_linear_algebra/c_matrix_decompositions.cpp
detkit/_c_linear_algebra/c_matrix_decompositions.h
detkit/_c_linear_algebra/c_matrix_decompositions.pxd
detkit/_c_linear_algebra/c_matrix_functions.cpp
detkit/_c_linear_algebra/c_matrix_functions.h
detkit-0.12.3.dist-info/DELVEWHEEL
detkit-0.12.3.dist-info/METADATA
detkit-0.12.3.dist-info/RECORD
detkit-0.12.3.dist-info/top_level.txt
detkit-0.12.3.dist-info/WHEEL
detkit-0.12.3.dist-info/licenses/AUTHORS.txt
detkit-0.12.3.dist-info/licenses/LICENSE.txt
