Metadata-Version: 2.4
Name: detkit
Version: 0.12.3
Summary: Matrix determinant toolkit
Home-page: https://github.com/ameli/detkit
Download-URL: https://github.com/ameli/detkit/archive/main.zip
Author: Siavash Ameli
Author-email: sameli@berkeley.edu
Project-URL: Documentation, https://github.com/ameli/detkit/blob/main/README.rst
Project-URL: Source, https://github.com/ameli/detkit
Project-URL: Tracker, https://github.com/ameli/detkit/issues
Keywords: matrix-computations cholesky-decomposition logdet
Platform: Linux
Platform: OSX
Platform: Windows
Classifier: Programming Language :: C++
Classifier: Programming Language :: Cython
Classifier: Programming Language :: Python
Classifier: Programming Language :: Python :: 3.9
Classifier: Programming Language :: Python :: 3.10
Classifier: Programming Language :: Python :: 3.11
Classifier: Programming Language :: Python :: 3.12
Classifier: Programming Language :: Python :: 3.13
Classifier: Programming Language :: Python :: Implementation :: CPython
Classifier: Programming Language :: Python :: Implementation :: PyPy
Classifier: License :: OSI Approved :: BSD License
Classifier: Operating System :: Unix
Classifier: Operating System :: POSIX
Classifier: Operating System :: POSIX :: Linux
Classifier: Operating System :: Microsoft :: Windows
Classifier: Operating System :: MacOS
Classifier: Natural Language :: English
Classifier: Intended Audience :: Science/Research
Classifier: Intended Audience :: Developers
Classifier: Topic :: Software Development
Classifier: Topic :: Software Development :: Libraries :: Python Modules
Classifier: Topic :: Scientific/Engineering
Classifier: Topic :: Scientific/Engineering :: Mathematics
Classifier: Topic :: Scientific/Engineering :: Artificial Intelligence
Requires-Python: >=3.8
License-File: LICENSE.txt
License-File: AUTHORS.txt
Requires-Dist: numpy>1.11
Requires-Dist: scipy>=1.5
Requires-Dist: matplotlib>=2.0
Requires-Dist: texplot
Requires-Dist: pooch
Requires-Dist: psutil; platform_python_implementation == "CPython"
Requires-Dist: zarr; platform_python_implementation == "CPython"
Requires-Dist: dask; platform_python_implementation == "CPython"
Requires-Dist: distributed; platform_python_implementation == "CPython"
Requires-Dist: tensorstore; platform_python_implementation == "CPython"
Provides-Extra: test
Requires-Dist: pytest; extra == "test"
Provides-Extra: docs
Requires-Dist: sphinx; extra == "docs"
Requires-Dist: sphinx-math-dollar; extra == "docs"
Requires-Dist: sphinx-toggleprompt<0.4; extra == "docs"
Requires-Dist: pydata_sphinx_theme==0.9.0; extra == "docs"
Requires-Dist: graphviz; extra == "docs"
Requires-Dist: sphinx-automodapi; extra == "docs"
Requires-Dist: numpydoc; extra == "docs"
Requires-Dist: nbsphinx; extra == "docs"
Requires-Dist: sphinx_design; extra == "docs"
Requires-Dist: sphinx-multitoc-numbering; extra == "docs"
Requires-Dist: sphinx-prompt>=1.10.0; extra == "docs"
Requires-Dist: sphinx-copybutton; extra == "docs"
Requires-Dist: sphinxext-opengraph; extra == "docs"
Requires-Dist: scipy; extra == "docs"
Dynamic: author
Dynamic: author-email
Dynamic: classifier
Dynamic: description
Dynamic: description-content-type
Dynamic: download-url
Dynamic: home-page
Dynamic: keywords
Dynamic: license-file
Dynamic: platform
Dynamic: project-url
Dynamic: provides-extra
Dynamic: requires-dist
Dynamic: requires-python
Dynamic: summary
